README.md
setup.py
qmix/__init__.py
qmix/circuit.py
qmix/harmonic_balance.py
qmix/qtcurrent.py
qmix/respfn.py
qmix.egg-info/PKG-INFO
qmix.egg-info/SOURCES.txt
qmix.egg-info/dependency_links.txt
qmix.egg-info/requires.txt
qmix.egg-info/top_level.txt
qmix/exp/__init__.py
qmix/exp/clean_data.py
qmix/exp/exp_data.py
qmix/exp/if_data.py
qmix/exp/if_response.py
qmix/exp/iv_data.py
qmix/exp/parameters.py
qmix/mathfn/__init__.py
qmix/mathfn/filters.py
qmix/mathfn/ivcurve_models.py
qmix/mathfn/kktrans.py
qmix/mathfn/misc.py
qmix/misc/__init__.py
qmix/misc/progbar.py
qmix/misc/terminal.py
tests/__init__.py
tests/test_circuit.py
tests/test_clean_data.py
tests/test_exp_data.py
tests/test_harmonic_balance.py
tests/test_if_reponse.py
tests/test_ivcurve-models.py
tests/test_kktrans.py
tests/test_mathfn.py
tests/test_qtcurrent.py
tests/test_respfn.py