Metadata-Version: 2.1
Name: qmix
Version: 1.0.6
Summary: Simulate SIS mixer operation
Home-page: https://garrettj403.github.io/QMix/
Author: John Garrett
Author-email: garrettj403@gmail.com
License: GPL v3
Project-URL: Changelog, https://github.com/garrettj403/QMix/blob/master/CHANGES.md
Project-URL: Issue Tracker, https://github.com/garrettj403/QMix/issues
Keywords: SIS mixers,radio astronomy,superconducting detectors,terahertz instrumentation,Python
Platform: any
Classifier: Development Status :: 5 - Production/Stable
Classifier: Intended Audience :: Science/Research
Classifier: License :: OSI Approved :: GNU General Public License v3 (GPLv3)
Classifier: Natural Language :: English
Classifier: Programming Language :: Python :: 3.5
Classifier: Programming Language :: Python :: 3.6
Classifier: Programming Language :: Python :: 3.7
Classifier: Programming Language :: Python :: 3.8
Classifier: Topic :: Scientific/Engineering :: Physics
Classifier: Topic :: Scientific/Engineering :: Astronomy
Provides-Extra: test
